pypbar/__init__.py
pypbar/py.typed
pypbar-0.2.0.dist-info/LICENSE
pypbar-0.2.0.dist-info/METADATA
pypbar-0.2.0.dist-info/WHEEL
pypbar-0.2.0.dist-info/top_level.txt
pypbar-0.2.0.dist-info/RECORD
