Metadata-Version: 2.1
Name: pypbar
Version: 0.2.0
Summary: Python ProgressBar
Home-page: https://github.com/koviubi56/pypbar
Author: Koviubi56
Author-email: koviubi56@duck.com
License: GPL
Keywords: progress,bar,progressbar
Platform: unix
Platform: linux
Platform: osx
Platform: cygwin
Platform: win32
Classifier: Development Status :: 4 - Beta
Classifier: License :: OSI Approved :: GNU General Public License v3 or later (GPLv3+)
Classifier: Programming Language :: Python :: 3
Classifier: Programming Language :: Python :: 3 :: Only
Classifier: Programming Language :: Python :: 3.7
Classifier: Programming Language :: Python :: 3.8
Classifier: Programming Language :: Python :: 3.9
Classifier: Programming Language :: Python :: 3.10
Classifier: Programming Language :: Python :: 3.11
Requires-Python: >=3.7
License-File: LICENSE
Requires-Dist: typing-extensions (>=4.0.0)
